pymetr/__init__.py
pymetr/instruments.py
pymetr/interfaces.py
pymetr/oscilloscope/__init__.py
pymetr/oscilloscope/acquire.py
pymetr/oscilloscope/channel.py
pymetr/oscilloscope/core.py
pymetr/oscilloscope/timebase.py
pymetr/oscilloscope/trigger.py
pymetr/oscilloscope/waveform.py
pymetr/oscilloscope/wavegen.py
utilities/__init__.py
utilities/_init_dump.py
utilities/_project_tree.py
utilities/_rst_dump.py
utilities/decorators.py
utilities/utils.py
PyMetr-0.1.0.dist-info/LICENSE
PyMetr-0.1.0.dist-info/METADATA
PyMetr-0.1.0.dist-info/WHEEL
PyMetr-0.1.0.dist-info/top_level.txt
PyMetr-0.1.0.dist-info/RECORD
