Metadata-Version: 2.1
Name: PyMetr
Version: 0.1.0
Summary: A comprehensive Python library for connecting, controlling, and managing test and measurement instruments.
Home-page: https://github.com/pymetr/pymetr
Author: Ryan.C.Smith
Author-email: bellstate@gmail.com
Keywords: instrumentation control SCPI test measurement plotting real-time data
License-File: LICENSE
